.DS_Store
pyHSICLasso/__init__.py
pyHSICLasso/api.py
pyHSICLasso/hsic_lasso.py
pyHSICLasso/input_data.py
pyHSICLasso/kernel_tools.py
pyHSICLasso/nlars.py
pyHSICLasso/plot_figure.py
pyHSICLasso-1.4.2.dist-info/LICENSE
pyHSICLasso-1.4.2.dist-info/METADATA
pyHSICLasso-1.4.2.dist-info/WHEEL
pyHSICLasso-1.4.2.dist-info/top_level.txt
pyHSICLasso-1.4.2.dist-info/RECORD
