Metadata-Version: 2.1
Name: pyHSICLasso
Version: 1.4.2
Summary: Supervised, nonlinear feature selection method for high-dimensional datasets.
Home-page: http://www.makotoyamada-ml.com/hsiclasso.html
Author: Makoto Yamada
Author-email: makoto.yamada@riken.jp
License: MIT
Download-URL: https://github.com/riken-aip/pyHSICLasso
Keywords: HSIC Lasso HSICLasso feature-selection feature-extraction machine-learning nonlinear data-science
Platform: python2.7
Platform: python3.4
Platform: python3.5
Platform: python3.6
Classifier: Development Status :: 5 - Production/Stable
Classifier: Intended Audience :: Science/Research
Classifier: Intended Audience :: Developers
Classifier: License :: OSI Approved :: MIT License
Classifier: Programming Language :: Python
Classifier: Programming Language :: Python :: 2
Classifier: Programming Language :: Python :: 2.7
Classifier: Programming Language :: Python :: 3
Classifier: Programming Language :: Python :: 3.4
Classifier: Programming Language :: Python :: 3.5
Classifier: Programming Language :: Python :: 3.6
Classifier: Topic :: Scientific/Engineering
Requires-Dist: future
Requires-Dist: matplotlib
Requires-Dist: numpy
Requires-Dist: pandas
Requires-Dist: pytest
Requires-Dist: scipy
Requires-Dist: six
Requires-Dist: seaborn
Requires-Dist: joblib
